qstash/__init__.py
qstash/asyncio/__init__.py
qstash/asyncio/client.py
qstash/asyncio/dlq.py
qstash/asyncio/http.py
qstash/asyncio/log.py
qstash/asyncio/message.py
qstash/asyncio/queue.py
qstash/asyncio/schedule.py
qstash/asyncio/signing_key.py
qstash/asyncio/url_group.py
qstash/chat.py
qstash/client.py
qstash/dlq.py
qstash/errors.py
qstash/http.py
qstash/log.py
qstash/message.py
qstash/py.typed
qstash/queue.py
qstash/receiver.py
qstash/schedule.py
qstash/signing_key.py
qstash/url_group.py
qstash-3.0.0.dist-info/LICENSE
qstash-3.0.0.dist-info/METADATA
qstash-3.0.0.dist-info/WHEEL
qstash-3.0.0.dist-info/RECORD
